HtmlCssInclude.py
MANIFEST.in
README
setup.cfg
setup.py
HtmlCssInclude.egg-info/PKG-INFO
HtmlCssInclude.egg-info/SOURCES.txt
HtmlCssInclude.egg-info/dependency_links.txt
HtmlCssInclude.egg-info/top_level.txt
testdata/sample.css
testdata/sample.html