Metadata-Version: 1.0
Name: HtmlCssInclude
Version: 0.1.2
Summary: HtmlCssInclude convert css to inline style for mobile
Home-page: UNKNOWN
Author: UNKNOWN
Author-email: hata.hirotaka@gamil.com
License: PSL
Platform: UNKNOWN
Classifier: Development Status :: 3 - Alpha
Classifier: License :: OSI Approved :: Python Software Foundation License
Classifier: Programming Language :: Python
Classifier: Topic :: Text Processing :: Markup :: HTML
